odoo/addons/account_invoice_ubl/README.rst
odoo/addons/account_invoice_ubl/__init__.py
odoo/addons/account_invoice_ubl/__manifest__.py
odoo/addons/account_invoice_ubl/hooks.py
odoo/addons/account_invoice_ubl/i18n/account_invoice_ubl.pot
odoo/addons/account_invoice_ubl/i18n/de.po
odoo/addons/account_invoice_ubl/i18n/es.po
odoo/addons/account_invoice_ubl/i18n/fr.po
odoo/addons/account_invoice_ubl/i18n/hr.po
odoo/addons/account_invoice_ubl/i18n/nl.po
odoo/addons/account_invoice_ubl/i18n/pt.po
odoo/addons/account_invoice_ubl/models/__init__.py
odoo/addons/account_invoice_ubl/models/account_invoice.py
odoo/addons/account_invoice_ubl/models/ir_actions_report.py
odoo/addons/account_invoice_ubl/models/res_company.py
odoo/addons/account_invoice_ubl/models/res_config_settings.py
odoo/addons/account_invoice_ubl/readme/CONFIGURE.rst
odoo/addons/account_invoice_ubl/readme/CONTRIBUTORS.rst
odoo/addons/account_invoice_ubl/readme/DESCRIPTION.rst
odoo/addons/account_invoice_ubl/static/description/icon.png
odoo/addons/account_invoice_ubl/static/description/index.html
odoo/addons/account_invoice_ubl/tests/__init__.py
odoo/addons/account_invoice_ubl/tests/test_ubl_generate.py
odoo/addons/account_invoice_ubl/views/account_invoice.xml
odoo/addons/account_invoice_ubl/views/res_config_settings.xml
odoo12_addon_account_invoice_ubl-12.0.1.1.2.dist-info/METADATA
odoo12_addon_account_invoice_ubl-12.0.1.1.2.dist-info/WHEEL
odoo12_addon_account_invoice_ubl-12.0.1.1.2.dist-info/top_level.txt
odoo12_addon_account_invoice_ubl-12.0.1.1.2.dist-info/RECORD
