Metadata-Version: 2.1
Name: odoo12-addon-account-invoice-ubl
Version: 12.0.1.1.2
Summary: Generate UBL XML file for customer invoices/refunds
Home-page: https://github.com/OCA/edi
Author: Akretion,Odoo Community Association (OCA)
Author-email: support@odoo-community.org
License: AGPL-3
Platform: UNKNOWN
Classifier: Programming Language :: Python
Classifier: Framework :: Odoo
Classifier: Framework :: Odoo :: 12.0
Classifier: License :: OSI Approved :: GNU Affero General Public License v3
Requires-Python: >=3.5
Requires-Dist: odoo12-addon-account-e-invoice-generate
Requires-Dist: odoo12-addon-account-payment-partner
Requires-Dist: odoo12-addon-account-tax-unece
Requires-Dist: odoo12-addon-base-ubl-payment
Requires-Dist: odoo <12.1dev,>=12.0a
